collective.bluesky-1.0.0a3-py3.10-nspkg.pth
collective/bluesky/__init__.py
collective/bluesky/app.py
collective/bluesky/configure.zcml
collective/bluesky/interfaces.py
collective/bluesky/registry.py
collective/bluesky/settings.py
collective/bluesky/testing.py
collective/bluesky/actions/__init__.py
collective/bluesky/actions/bluesky.pt
collective/bluesky/actions/bluesky.py
collective/bluesky/actions/configure.zcml
collective/bluesky/locales/collective.bluesky.pot
collective/bluesky/locales/update.py
collective/bluesky/locales/de/LC_MESSAGES/collective.bluesky.po
collective/bluesky/locales/en/LC_MESSAGES/collective.bluesky.po
collective/bluesky/locales/es/LC_MESSAGES/collective.bluesky.po
collective/bluesky/locales/pt_BR/LC_MESSAGES/collective.bluesky.po
collective/bluesky/startup/__init__.py
collective/bluesky/utils/__init__.py
collective/bluesky/utils/content.py
collective/bluesky/utils/tools.py
collective/bluesky/utils/username.py
collective/bluesky/vocabularies/__init__.py
collective/bluesky/vocabularies/apps.py
collective/bluesky/vocabularies/configure.zcml
collective.bluesky-1.0.0a3.dist-info/LICENSE.GPL
collective.bluesky-1.0.0a3.dist-info/METADATA
collective.bluesky-1.0.0a3.dist-info/WHEEL
collective.bluesky-1.0.0a3.dist-info/entry_points.txt
collective.bluesky-1.0.0a3.dist-info/namespace_packages.txt
collective.bluesky-1.0.0a3.dist-info/top_level.txt
collective.bluesky-1.0.0a3.dist-info/RECORD
