Metadata-Version: 2.1
Name: collective.bluesky
Version: 1.0.0a3
Summary: Bluesky integration for Plone.
Home-page: https://pypi.python.org/pypi/collective.bluesky
Author: Érico Andrei
Author-email: ericof@plone.org
License: GPL version 2
Project-URL: PyPI, https://pypi.python.org/pypi/collective.bluesky
Project-URL: Source, https://github.com/collective/collective.bluesky
Project-URL: Tracker, https://github.com/collective/collective.bluesky/issues
Project-URL: Documentation, https://collective.github.io/collective.bluesky
Keywords: Python Plone Bluesky ContentRules SocialNetwork
Classifier: Development Status :: 3 - Alpha
Classifier: Environment :: Web Environment
Classifier: Framework :: Plone
Classifier: Framework :: Plone :: Addon
Classifier: Framework :: Plone :: 6.0
Classifier: Programming Language :: Python
Classifier: Programming Language :: Python :: 3.8
Classifier: Programming Language :: Python :: 3.9
Classifier: Programming Language :: Python :: 3.10
Classifier: Programming Language :: Python :: 3.11
Classifier: Operating System :: OS Independent
Classifier: License :: OSI Approved :: GNU General Public License v2 (GPLv2)
Requires-Python: >=3.8.0
License-File: LICENSE.GPL
Requires-Dist: prettyconf
Requires-Dist: Plone
Requires-Dist: setuptools
Requires-Dist: requests
Requires-Dist: plone.restapi (>=8.34.0)
Provides-Extra: test
Requires-Dist: gocept.pytestlayer ; extra == 'test'
Requires-Dist: plone.app.testing ; extra == 'test'
Requires-Dist: plone.restapi[test] ; extra == 'test'
Requires-Dist: pytest-cov ; extra == 'test'
Requires-Dist: pytest-plone (>=0.2.0) ; extra == 'test'
Requires-Dist: pytest-docker ; extra == 'test'
Requires-Dist: pytest-mock ; extra == 'test'
Requires-Dist: pytest ; extra == 'test'
Requires-Dist: zest.releaser[recommended] ; extra == 'test'
Requires-Dist: zestreleaser.towncrier ; extra == 'test'
Requires-Dist: requests-mock ; extra == 'test'
